[
    {
        "id": "0",
        "nome": "I Love You But I Love Me More",
        "artista": "Marina",
        "foto": "https://firebasestorage.googleapis.com/v0/b/music-player-c978b.appspot.com/o/1.jpg?alt=media&token=0b9b9297-54cb-45a2-b69e-c5ecaef2dff2&_gl=1*18goaqu*_ga*MTE0MzkzNjEyMi4xNjg0MjAwMDEy*_ga_CW55HF8NVT*MTY4NTg5MzkxOS42LjEuMTY4NTg5Mzk2Mi4wLjAuMA..",
        "audio": "https://firebasestorage.googleapis.com/v0/b/music-player-c978b.appspot.com/o/1.mp3?alt=media&token=41d3e475-4c6b-4e97-b295-27ba3acb5b12&_gl=1*jw4xi8*_ga*MTE0MzkzNjEyMi4xNjg0MjAwMDEy*_ga_CW55HF8NVT*MTY4NTg5MzkxOS42LjEuMTY4NTg5MzkzMi4wLjAuMA.."
    },
    {
        "id": "1",
        "nome": "Running Out Of Time",
        "artista": "Paramore",
        "foto": "https://firebasestorage.googleapis.com/v0/b/music-player-c978b.appspot.com/o/2.jpg?alt=media&token=e6fbcbd6-4283-4011-8dd7-35d9fe06f22b&_gl=1*djfod8*_ga*MTE0MzkzNjEyMi4xNjg0MjAwMDEy*_ga_CW55HF8NVT*MTY4NTg5OTA4Mi43LjEuMTY4NTg5OTA5Ni4wLjAuMA..",
        "audio": "https://firebasestorage.googleapis.com/v0/b/music-player-c978b.appspot.com/o/2.mp3?alt=media&token=bf2536c0-207d-47b3-9dbd-be5ca6fd5df8&_gl=1*108tt7p*_ga*MTE0MzkzNjEyMi4xNjg0MjAwMDEy*_ga_CW55HF8NVT*MTY4NTg5OTA4Mi43LjEuMTY4NTg5OTExOS4wLjAuMA.."
    }

]